{
  "nodes": [
    {
      "id": "build_gradle_kts",
      "label": "build.gradle.kts",
      "file_type": "code",
      "source_file": "build.gradle.kts",
      "source_location": "L1"
    },
    {
      "id": "settings_gradle_kts",
      "label": "settings.gradle.kts",
      "file_type": "code",
      "source_file": "settings.gradle.kts",
      "source_location": "L1"
    },
    {
      "id": "app_build_gradle_kts",
      "label": "build.gradle.kts",
      "file_type": "code",
      "source_file": "app\\build.gradle.kts",
      "source_location": "L1"
    },
    {
      "id": "app_src_androidtest_java_com_jarvis_app_exampleinstrumentedtest_kt",
      "label": "ExampleInstrumentedTest.kt",
      "file_type": "code",
      "source_file": "app\\src\\androidTest\\java\\com\\jarvis\\app\\ExampleInstrumentedTest.kt",
      "source_location": "L1"
    },
    {
      "id": "exampleinstrumentedtest_exampleinstrumentedtest",
      "label": "ExampleInstrumentedTest",
      "file_type": "code",
      "source_file": "app\\src\\androidTest\\java\\com\\jarvis\\app\\ExampleInstrumentedTest.kt",
      "source_location": "L16"
    },
    {
      "id": "exampleinstrumentedtest_exampleinstrumentedtest_useappcontext",
      "label": ".useAppContext()",
      "file_type": "code",
      "source_file": "app\\src\\androidTest\\java\\com\\jarvis\\app\\ExampleInstrumentedTest.kt",
      "source_location": "L18"
    },
    {
      "id": "app_src_main_java_com_jarvis_app_jarvisaccessibilityservice_kt",
      "label": "JarvisAccessibilityService.kt",
      "file_type": "code",
      "source_file": "app\\src\\main\\java\\com\\jarvis\\app\\JarvisAccessibilityService.kt",
      "source_location": "L1"
    },
    {
      "id": "jarvisaccessibilityservice_jarvisaccessibilityservice",
      "label": "JarvisAccessibilityService",
      "file_type": "code",
      "source_file": "app\\src\\main\\java\\com\\jarvis\\app\\JarvisAccessibilityService.kt",
      "source_location": "L9"
    },
    {
      "id": "jarvisaccessibilityservice_jarvisaccessibilityservice_onserviceconnected",
      "label": ".onServiceConnected()",
      "file_type": "code",
      "source_file": "app\\src\\main\\java\\com\\jarvis\\app\\JarvisAccessibilityService.kt",
      "source_location": "L16"
    },
    {
      "id": "jarvisaccessibilityservice_jarvisaccessibilityservice_onaccessibilityevent",
      "label": ".onAccessibilityEvent()",
      "file_type": "code",
      "source_file": "app\\src\\main\\java\\com\\jarvis\\app\\JarvisAccessibilityService.kt",
      "source_location": "L28"
    },
    {
      "id": "jarvisaccessibilityservice_jarvisaccessibilityservice_oninterrupt",
      "label": ".onInterrupt()",
      "file_type": "code",
      "source_file": "app\\src\\main\\java\\com\\jarvis\\app\\JarvisAccessibilityService.kt",
      "source_location": "L46"
    },
    {
      "id": "jarvisaccessibilityservice_jarvisaccessibilityservice_ondestroy",
      "label": ".onDestroy()",
      "file_type": "code",
      "source_file": "app\\src\\main\\java\\com\\jarvis\\app\\JarvisAccessibilityService.kt",
      "source_location": "L51"
    },
    {
      "id": "jarvisaccessibilityservice_jarvisaccessibilityservice_extracttext",
      "label": ".extractText()",
      "file_type": "code",
      "source_file": "app\\src\\main\\java\\com\\jarvis\\app\\JarvisAccessibilityService.kt",
      "source_location": "L56"
    },
    {
      "id": "app_src_main_java_com_jarvis_app_jarvisproactive_kt",
      "label": "JarvisProactive.kt",
      "file_type": "code",
      "source_file": "app\\src\\main\\java\\com\\jarvis\\app\\JarvisProactive.kt",
      "source_location": "L1"
    },
    {
      "id": "jarvisproactive_jarvisproactive",
      "label": "JarvisProactive",
      "file_type": "code",
      "source_file": "app\\src\\main\\java\\com\\jarvis\\app\\JarvisProactive.kt",
      "source_location": "L11"
    },
    {
      "id": "jarvisproactive_jarvisproactive_startmonitoring",
      "label": ".startMonitoring()",
      "file_type": "code",
      "source_file": "app\\src\\main\\java\\com\\jarvis\\app\\JarvisProactive.kt",
      "source_location": "L15"
    },
    {
      "id": "jarvisproactive_jarvisproactive_stopmonitoring",
      "label": ".stopMonitoring()",
      "file_type": "code",
      "source_file": "app\\src\\main\\java\\com\\jarvis\\app\\JarvisProactive.kt",
      "source_location": "L29"
    },
    {
      "id": "jarvisproactive_jarvisproactive_checkall",
      "label": ".checkAll()",
      "file_type": "code",
      "source_file": "app\\src\\main\\java\\com\\jarvis\\app\\JarvisProactive.kt",
      "source_location": "L34"
    },
    {
      "id": "jarvisproactive_jarvisproactive_checkcalendarreminders",
      "label": ".checkCalendarReminders()",
      "file_type": "code",
      "source_file": "app\\src\\main\\java\\com\\jarvis\\app\\JarvisProactive.kt",
      "source_location": "L47"
    },
    {
      "id": "jarvisproactive_jarvisproactive_checkbattery",
      "label": ".checkBattery()",
      "file_type": "code",
      "source_file": "app\\src\\main\\java\\com\\jarvis\\app\\JarvisProactive.kt",
      "source_location": "L74"
    },
    {
      "id": "app_src_main_java_com_jarvis_app_jarviswidgetprovider_kt",
      "label": "JarvisWidgetProvider.kt",
      "file_type": "code",
      "source_file": "app\\src\\main\\java\\com\\jarvis\\app\\JarvisWidgetProvider.kt",
      "source_location": "L1"
    },
    {
      "id": "jarviswidgetprovider_jarviswidgetprovider",
      "label": "JarvisWidgetProvider",
      "file_type": "code",
      "source_file": "app\\src\\main\\java\\com\\jarvis\\app\\JarvisWidgetProvider.kt",
      "source_location": "L16"
    },
    {
      "id": "jarviswidgetprovider_jarviswidgetprovider_onupdate",
      "label": ".onUpdate()",
      "file_type": "code",
      "source_file": "app\\src\\main\\java\\com\\jarvis\\app\\JarvisWidgetProvider.kt",
      "source_location": "L18"
    },
    {
      "id": "jarviswidgetprovider_updatewidget",
      "label": "updateWidget()",
      "file_type": "code",
      "source_file": "app\\src\\main\\java\\com\\jarvis\\app\\JarvisWidgetProvider.kt",
      "source_location": "L25"
    },
    {
      "id": "app_src_main_java_com_jarvis_app_mainactivity_kt",
      "label": "MainActivity.kt",
      "file_type": "code",
      "source_file": "app\\src\\main\\java\\com\\jarvis\\app\\MainActivity.kt",
      "source_location": "L1"
    },
    {
      "id": "mainactivity_chatmessage",
      "label": "ChatMessage",
      "file_type": "code",
      "source_file": "app\\src\\main\\java\\com\\jarvis\\app\\MainActivity.kt",
      "source_location": "L71"
    },
    {
      "id": "mainactivity_mainactivity",
      "label": "MainActivity",
      "file_type": "code",
      "source_file": "app\\src\\main\\java\\com\\jarvis\\app\\MainActivity.kt",
      "source_location": "L77"
    },
    {
      "id": "mainactivity_mainactivity_oncreate",
      "label": ".onCreate()",
      "file_type": "code",
      "source_file": "app\\src\\main\\java\\com\\jarvis\\app\\MainActivity.kt",
      "source_location": "L99"
    },
    {
      "id": "mainactivity_mainactivity_oninit",
      "label": ".onInit()",
      "file_type": "code",
      "source_file": "app\\src\\main\\java\\com\\jarvis\\app\\MainActivity.kt",
      "source_location": "L118"
    },
    {
      "id": "mainactivity_mainactivity_ondestroy",
      "label": ".onDestroy()",
      "file_type": "code",
      "source_file": "app\\src\\main\\java\\com\\jarvis\\app\\MainActivity.kt",
      "source_location": "L137"
    },
    {
      "id": "mainactivity_mainactivity_shutdownapp",
      "label": ".shutdownApp()",
      "file_type": "code",
      "source_file": "app\\src\\main\\java\\com\\jarvis\\app\\MainActivity.kt",
      "source_location": "L145"
    },
    {
      "id": "mainactivity_mainactivity_speakwithtts",
      "label": ".speakWithTTS()",
      "file_type": "code",
      "source_file": "app\\src\\main\\java\\com\\jarvis\\app\\MainActivity.kt",
      "source_location": "L159"
    },
    {
      "id": "mainactivity_mainactivity_speakwithelevenlabs",
      "label": ".speakWithElevenLabs()",
      "file_type": "code",
      "source_file": "app\\src\\main\\java\\com\\jarvis\\app\\MainActivity.kt",
      "source_location": "L169"
    },
    {
      "id": "mainactivity_mainactivity_speaktext",
      "label": ".speakText()",
      "file_type": "code",
      "source_file": "app\\src\\main\\java\\com\\jarvis\\app\\MainActivity.kt",
      "source_location": "L207"
    },
    {
      "id": "mainactivity_mainactivity_startlisteninginternal",
      "label": ".startListeningInternal()",
      "file_type": "code",
      "source_file": "app\\src\\main\\java\\com\\jarvis\\app\\MainActivity.kt",
      "source_location": "L213"
    },
    {
      "id": "mainactivity_mainactivity_stoplistening",
      "label": ".stopListening()",
      "file_type": "code",
      "source_file": "app\\src\\main\\java\\com\\jarvis\\app\\MainActivity.kt",
      "source_location": "L276"
    },
    {
      "id": "mainactivity_mainactivity_openapp",
      "label": ".openApp()",
      "file_type": "code",
      "source_file": "app\\src\\main\\java\\com\\jarvis\\app\\MainActivity.kt",
      "source_location": "L281"
    },
    {
      "id": "mainactivity_mainactivity_extractafter",
      "label": ".extractAfter()",
      "file_type": "code",
      "source_file": "app\\src\\main\\java\\com\\jarvis\\app\\MainActivity.kt",
      "source_location": "L305"
    },
    {
      "id": "mainactivity_mainactivity_extractnumber",
      "label": ".extractNumber()",
      "file_type": "code",
      "source_file": "app\\src\\main\\java\\com\\jarvis\\app\\MainActivity.kt",
      "source_location": "L313"
    },
    {
      "id": "mainactivity_mainactivity_extracttime",
      "label": ".extractTime()",
      "file_type": "code",
      "source_file": "app\\src\\main\\java\\com\\jarvis\\app\\MainActivity.kt",
      "source_location": "L324"
    },
    {
      "id": "mainactivity_mainactivity_parsehourword",
      "label": ".parseHourWord()",
      "file_type": "code",
      "source_file": "app\\src\\main\\java\\com\\jarvis\\app\\MainActivity.kt",
      "source_location": "L371"
    },
    {
      "id": "mainactivity_mainactivity_extractdate",
      "label": ".extractDate()",
      "file_type": "code",
      "source_file": "app\\src\\main\\java\\com\\jarvis\\app\\MainActivity.kt",
      "source_location": "L378"
    },
    {
      "id": "mainactivity_mainactivity_extracteventtitle",
      "label": ".extractEventTitle()",
      "file_type": "code",
      "source_file": "app\\src\\main\\java\\com\\jarvis\\app\\MainActivity.kt",
      "source_location": "L416"
    },
    {
      "id": "mainactivity_mainactivity_readcalendarevents",
      "label": ".readCalendarEvents()",
      "file_type": "code",
      "source_file": "app\\src\\main\\java\\com\\jarvis\\app\\MainActivity.kt",
      "source_location": "L429"
    },
    {
      "id": "mainactivity_mainactivity_createcalendareventdirect",
      "label": ".createCalendarEventDirect()",
      "file_type": "code",
      "source_file": "app\\src\\main\\java\\com\\jarvis\\app\\MainActivity.kt",
      "source_location": "L473"
    },
    {
      "id": "mainactivity_mainactivity_deletecalendarevent",
      "label": ".deleteCalendarEvent()",
      "file_type": "code",
      "source_file": "app\\src\\main\\java\\com\\jarvis\\app\\MainActivity.kt",
      "source_location": "L494"
    },
    {
      "id": "mainactivity_mainactivity_trysetalarm",
      "label": ".trySetAlarm()",
      "file_type": "code",
      "source_file": "app\\src\\main\\java\\com\\jarvis\\app\\MainActivity.kt",
      "source_location": "L521"
    },
    {
      "id": "mainactivity_mainactivity_sendmediakey",
      "label": ".sendMediaKey()",
      "file_type": "code",
      "source_file": "app\\src\\main\\java\\com\\jarvis\\app\\MainActivity.kt",
      "source_location": "L553"
    },
    {
      "id": "mainactivity_mainactivity_researchtopic",
      "label": ".researchTopic()",
      "file_type": "code",
      "source_file": "app\\src\\main\\java\\com\\jarvis\\app\\MainActivity.kt",
      "source_location": "L575"
    },
    {
      "id": "mainactivity_mainactivity_savepdf",
      "label": ".savePdf()",
      "file_type": "code",
      "source_file": "app\\src\\main\\java\\com\\jarvis\\app\\MainActivity.kt",
      "source_location": "L689"
    },
    {
      "id": "mainactivity_mainactivity_getweather",
      "label": ".getWeather()",
      "file_type": "code",
      "source_file": "app\\src\\main\\java\\com\\jarvis\\app\\MainActivity.kt",
      "source_location": "L783"
    },
    {
      "id": "mainactivity_mainactivity_getforecast",
      "label": ".getForecast()",
      "file_type": "code",
      "source_file": "app\\src\\main\\java\\com\\jarvis\\app\\MainActivity.kt",
      "source_location": "L808"
    },
    {
      "id": "mainactivity_mainactivity_gettopheadlines",
      "label": ".getTopHeadlines()",
      "file_type": "code",
      "source_file": "app\\src\\main\\java\\com\\jarvis\\app\\MainActivity.kt",
      "source_location": "L844"
    },
    {
      "id": "mainactivity_mainactivity_handlevoicecommand",
      "label": ".handleVoiceCommand()",
      "file_type": "code",
      "source_file": "app\\src\\main\\java\\com\\jarvis\\app\\MainActivity.kt",
      "source_location": "L888"
    },
    {
      "id": "mainactivity_mainactivity_jarvisscreen",
      "label": ".JarvisScreen()",
      "file_type": "code",
      "source_file": "app\\src\\main\\java\\com\\jarvis\\app\\MainActivity.kt",
      "source_location": "L1832"
    },
    {
      "id": "mainactivity_mainactivity_phasecolor",
      "label": ".phaseColor()",
      "file_type": "code",
      "source_file": "app\\src\\main\\java\\com\\jarvis\\app\\MainActivity.kt",
      "source_location": "L2085"
    },
    {
      "id": "mainactivity_mainactivity_arcreactormk6",
      "label": ".ArcReactorMk6()",
      "file_type": "code",
      "source_file": "app\\src\\main\\java\\com\\jarvis\\app\\MainActivity.kt",
      "source_location": "L2093"
    },
    {
      "id": "mainactivity_mainactivity_waveformbar",
      "label": ".WaveformBar()",
      "file_type": "code",
      "source_file": "app\\src\\main\\java\\com\\jarvis\\app\\MainActivity.kt",
      "source_location": "L2289"
    },
    {
      "id": "mainactivity_mainactivity_topbar",
      "label": ".TopBar()",
      "file_type": "code",
      "source_file": "app\\src\\main\\java\\com\\jarvis\\app\\MainActivity.kt",
      "source_location": "L2312"
    },
    {
      "id": "mainactivity_mainactivity_statusgridwide",
      "label": ".StatusGridWide()",
      "file_type": "code",
      "source_file": "app\\src\\main\\java\\com\\jarvis\\app\\MainActivity.kt",
      "source_location": "L2337"
    },
    {
      "id": "mainactivity_mainactivity_statcard",
      "label": ".StatCard()",
      "file_type": "code",
      "source_file": "app\\src\\main\\java\\com\\jarvis\\app\\MainActivity.kt",
      "source_location": "L2356"
    },
    {
      "id": "mainactivity_mainactivity_metricpanel",
      "label": ".MetricPanel()",
      "file_type": "code",
      "source_file": "app\\src\\main\\java\\com\\jarvis\\app\\MainActivity.kt",
      "source_location": "L2370"
    },
    {
      "id": "mainactivity_mainactivity_metricrow",
      "label": ".MetricRow()",
      "file_type": "code",
      "source_file": "app\\src\\main\\java\\com\\jarvis\\app\\MainActivity.kt",
      "source_location": "L2393"
    },
    {
      "id": "mainactivity_mainactivity_chatheader",
      "label": ".ChatHeader()",
      "file_type": "code",
      "source_file": "app\\src\\main\\java\\com\\jarvis\\app\\MainActivity.kt",
      "source_location": "L2411"
    },
    {
      "id": "mainactivity_mainactivity_phasechip",
      "label": ".PhaseChip()",
      "file_type": "code",
      "source_file": "app\\src\\main\\java\\com\\jarvis\\app\\MainActivity.kt",
      "source_location": "L2430"
    },
    {
      "id": "mainactivity_mainactivity_messagebubble",
      "label": ".MessageBubble()",
      "file_type": "code",
      "source_file": "app\\src\\main\\java\\com\\jarvis\\app\\MainActivity.kt",
      "source_location": "L2443"
    },
    {
      "id": "mainactivity_mainactivity_inputbar",
      "label": ".InputBar()",
      "file_type": "code",
      "source_file": "app\\src\\main\\java\\com\\jarvis\\app\\MainActivity.kt",
      "source_location": "L2473"
    },
    {
      "id": "mainactivity_mainactivity_jarvistheme",
      "label": ".JarvisTheme()",
      "file_type": "code",
      "source_file": "app\\src\\main\\java\\com\\jarvis\\app\\MainActivity.kt",
      "source_location": "L2514"
    },
    {
      "id": "mainactivity_mainactivity_loadmemoryfromfirebase",
      "label": ".loadMemoryFromFirebase()",
      "file_type": "code",
      "source_file": "app\\src\\main\\java\\com\\jarvis\\app\\MainActivity.kt",
      "source_location": "L2526"
    },
    {
      "id": "mainactivity_mainactivity_syncmessagetofirebase",
      "label": ".syncMessageToFirebase()",
      "file_type": "code",
      "source_file": "app\\src\\main\\java\\com\\jarvis\\app\\MainActivity.kt",
      "source_location": "L2536"
    },
    {
      "id": "mainactivity_mainactivity_saveconversationtofirebase",
      "label": ".saveConversationToFirebase()",
      "file_type": "code",
      "source_file": "app\\src\\main\\java\\com\\jarvis\\app\\MainActivity.kt",
      "source_location": "L2544"
    },
    {
      "id": "mainactivity_mainactivity_loadconversationfromfirebase",
      "label": ".loadConversationFromFirebase()",
      "file_type": "code",
      "source_file": "app\\src\\main\\java\\com\\jarvis\\app\\MainActivity.kt",
      "source_location": "L2552"
    },
    {
      "id": "mainactivity_mainactivity_sendtojarvis",
      "label": ".sendToJarvis()",
      "file_type": "code",
      "source_file": "app\\src\\main\\java\\com\\jarvis\\app\\MainActivity.kt",
      "source_location": "L2571"
    },
    {
      "id": "mainactivity_mainactivity_getgreeting",
      "label": ".getGreeting()",
      "file_type": "code",
      "source_file": "app\\src\\main\\java\\com\\jarvis\\app\\MainActivity.kt",
      "source_location": "L2701"
    },
    {
      "id": "app_src_main_java_com_jarvis_app_ui_theme_color_kt",
      "label": "Color.kt",
      "file_type": "code",
      "source_file": "app\\src\\main\\java\\com\\jarvis\\app\\ui\\theme\\Color.kt",
      "source_location": "L1"
    },
    {
      "id": "app_src_main_java_com_jarvis_app_ui_theme_theme_kt",
      "label": "Theme.kt",
      "file_type": "code",
      "source_file": "app\\src\\main\\java\\com\\jarvis\\app\\ui\\theme\\Theme.kt",
      "source_location": "L1"
    },
    {
      "id": "theme_jarvistheme",
      "label": "JarvisTheme()",
      "file_type": "code",
      "source_file": "app\\src\\main\\java\\com\\jarvis\\app\\ui\\theme\\Theme.kt",
      "source_location": "L36"
    },
    {
      "id": "app_src_main_java_com_jarvis_app_ui_theme_type_kt",
      "label": "Type.kt",
      "file_type": "code",
      "source_file": "app\\src\\main\\java\\com\\jarvis\\app\\ui\\theme\\Type.kt",
      "source_location": "L1"
    },
    {
      "id": "app_src_test_java_com_jarvis_app_exampleunittest_kt",
      "label": "ExampleUnitTest.kt",
      "file_type": "code",
      "source_file": "app\\src\\test\\java\\com\\jarvis\\app\\ExampleUnitTest.kt",
      "source_location": "L1"
    },
    {
      "id": "exampleunittest_exampleunittest",
      "label": "ExampleUnitTest",
      "file_type": "code",
      "source_file": "app\\src\\test\\java\\com\\jarvis\\app\\ExampleUnitTest.kt",
      "source_location": "L12"
    },
    {
      "id": "exampleunittest_exampleunittest_addition_iscorrect",
      "label": ".addition_isCorrect()",
      "file_type": "code",
      "source_file": "app\\src\\test\\java\\com\\jarvis\\app\\ExampleUnitTest.kt",
      "source_location": "L13"
    },
    {
      "id": "ic_launcher_hdpi",
      "label": "App Launcher Icon (hdpi)",
      "file_type": "image",
      "source_file": "app/src/main/res/mipmap-hdpi/ic_launcher.webp",
      "source_location": null,
      "source_url": null,
      "captured_at": null,
      "author": null,
      "contributor": null
    },
    {
      "id": "ic_launcher_mdpi",
      "label": "App Launcher Icon (mdpi)",
      "file_type": "image",
      "source_file": "app/src/main/res/mipmap-mdpi/ic_launcher.webp",
      "source_location": null,
      "source_url": null,
      "captured_at": null,
      "author": null,
      "contributor": null
    },
    {
      "id": "ic_launcher_xhdpi",
      "label": "App Launcher Icon (xhdpi)",
      "file_type": "image",
      "source_file": "app/src/main/res/mipmap-xhdpi/ic_launcher.webp",
      "source_location": null,
      "source_url": null,
      "captured_at": null,
      "author": null,
      "contributor": null
    },
    {
      "id": "ic_launcher_xxhdpi",
      "label": "App Launcher Icon (xxhdpi)",
      "file_type": "image",
      "source_file": "app/src/main/res/mipmap-xxhdpi/ic_launcher.webp",
      "source_location": null,
      "source_url": null,
      "captured_at": null,
      "author": null,
      "contributor": null
    },
    {
      "id": "ic_launcher_xxxhdpi",
      "label": "App Launcher Icon (xxxhdpi)",
      "file_type": "image",
      "source_file": "app/src/main/res/mipmap-xxxhdpi/ic_launcher.webp",
      "source_location": null,
      "source_url": null,
      "captured_at": null,
      "author": null,
      "contributor": null
    },
    {
      "id": "concept_android_robot_icon",
      "label": "Android Robot / Default Launcher Icon Design",
      "file_type": "concept",
      "source_file": null,
      "source_location": null,
      "source_url": null,
      "captured_at": null,
      "author": null,
      "contributor": null
    },
    {
      "id": "concept_green_grid_background",
      "label": "Green Grid Background Design Pattern",
      "file_type": "concept",
      "source_file": null,
      "source_location": null,
      "source_url": null,
      "captured_at": null,
      "author": null,
      "contributor": null
    },
    {
      "id": "concept_default_android_branding",
      "label": "Default Android App Branding (Unmodified)",
      "file_type": "concept",
      "source_file": null,
      "source_location": null,
      "source_url": null,
      "captured_at": null,
      "author": null,
      "contributor": null
    },
    {
      "id": "concept_mipmap_density_set",
      "label": "Android Mipmap Density-Specific Icon Set",
      "file_type": "concept",
      "source_file": null,
      "source_location": null,
      "source_url": null,
      "captured_at": null,
      "author": null,
      "contributor": null
    },
    {
      "id": "ic_launcher_round_hdpi",
      "label": "App Round Icon (hdpi)",
      "file_type": "image",
      "source_file": "app/src/main/res/mipmap-hdpi/ic_launcher_round.webp",
      "source_location": null,
      "source_url": null,
      "captured_at": null,
      "author": null,
      "contributor": null
    },
    {
      "id": "ic_launcher_round_mdpi",
      "label": "App Round Icon (mdpi)",
      "file_type": "image",
      "source_file": "app/src/main/res/mipmap-mdpi/ic_launcher_round.webp",
      "source_location": null,
      "source_url": null,
      "captured_at": null,
      "author": null,
      "contributor": null
    },
    {
      "id": "ic_launcher_round_xhdpi",
      "label": "App Round Icon (xhdpi)",
      "file_type": "image",
      "source_file": "app/src/main/res/mipmap-xhdpi/ic_launcher_round.webp",
      "source_location": null,
      "source_url": null,
      "captured_at": null,
      "author": null,
      "contributor": null
    },
    {
      "id": "ic_launcher_round_xxhdpi",
      "label": "App Round Icon (xxhdpi)",
      "file_type": "image",
      "source_file": "app/src/main/res/mipmap-xxhdpi/ic_launcher_round.webp",
      "source_location": null,
      "source_url": null,
      "captured_at": null,
      "author": null,
      "contributor": null
    },
    {
      "id": "ic_launcher_round_xxxhdpi",
      "label": "App Round Icon (xxxhdpi)",
      "file_type": "image",
      "source_file": "app/src/main/res/mipmap-xxxhdpi/ic_launcher_round.webp",
      "source_location": null,
      "source_url": null,
      "captured_at": null,
      "author": null,
      "contributor": null
    },
    {
      "id": "concept_green_palette",
      "label": "Green Color Palette (#4CAF50 range)",
      "file_type": "concept",
      "source_file": "app/src/main/res/mipmap-xxxhdpi/ic_launcher_round.webp",
      "source_location": null,
      "source_url": null,
      "captured_at": null,
      "author": null,
      "contributor": null
    },
    {
      "id": "concept_round_icon_shape",
      "label": "Round Icon Shape (Android Adaptive)",
      "file_type": "concept",
      "source_file": "app/src/main/res/mipmap-xxxhdpi/ic_launcher_round.webp",
      "source_location": null,
      "source_url": null,
      "captured_at": null,
      "author": null,
      "contributor": null
    },
    {
      "id": "concept_grid_background",
      "label": "Grid/Tile Background Pattern",
      "file_type": "concept",
      "source_file": "app/src/main/res/mipmap-xxxhdpi/ic_launcher_round.webp",
      "source_location": null,
      "source_url": null,
      "captured_at": null,
      "author": null,
      "contributor": null
    }
  ],
  "edges": [
    {
      "source": "app_src_androidtest_java_com_jarvis_app_exampleinstrumentedtest_kt",
      "target": "exampleinstrumentedtest_exampleinstrumentedtest",
      "relation": "contains",
      "confidence": "EXTRACTED",
      "source_file": "app\\src\\androidTest\\java\\com\\jarvis\\app\\ExampleInstrumentedTest.kt",
      "source_location": "L16",
      "weight": 1.0
    },
    {
      "source": "exampleinstrumentedtest_exampleinstrumentedtest",
      "target": "exampleinstrumentedtest_exampleinstrumentedtest_useappcontext",
      "relation": "method",
      "confidence": "EXTRACTED",
      "source_file": "app\\src\\androidTest\\java\\com\\jarvis\\app\\ExampleInstrumentedTest.kt",
      "source_location": "L18",
      "weight": 1.0
    },
    {
      "source": "app_src_main_java_com_jarvis_app_jarvisaccessibilityservice_kt",
      "target": "jarvisaccessibilityservice_jarvisaccessibilityservice",
      "relation": "contains",
      "confidence": "EXTRACTED",
      "source_file": "app\\src\\main\\java\\com\\jarvis\\app\\JarvisAccessibilityService.kt",
      "source_location": "L9",
      "weight": 1.0
    },
    {
      "source": "jarvisaccessibilityservice_jarvisaccessibilityservice",
      "target": "jarvisaccessibilityservice_jarvisaccessibilityservice_onserviceconnected",
      "relation": "method",
      "confidence": "EXTRACTED",
      "source_file": "app\\src\\main\\java\\com\\jarvis\\app\\JarvisAccessibilityService.kt",
      "source_location": "L16",
      "weight": 1.0
    },
    {
      "source": "jarvisaccessibilityservice_jarvisaccessibilityservice",
      "target": "jarvisaccessibilityservice_jarvisaccessibilityservice_onaccessibilityevent",
      "relation": "method",
      "confidence": "EXTRACTED",
      "source_file": "app\\src\\main\\java\\com\\jarvis\\app\\JarvisAccessibilityService.kt",
      "source_location": "L28",
      "weight": 1.0
    },
    {
      "source": "jarvisaccessibilityservice_jarvisaccessibilityservice",
      "target": "jarvisaccessibilityservice_jarvisaccessibilityservice_oninterrupt",
      "relation": "method",
      "confidence": "EXTRACTED",
      "source_file": "app\\src\\main\\java\\com\\jarvis\\app\\JarvisAccessibilityService.kt",
      "source_location": "L46",
      "weight": 1.0
    },
    {
      "source": "jarvisaccessibilityservice_jarvisaccessibilityservice",
      "target": "jarvisaccessibilityservice_jarvisaccessibilityservice_ondestroy",
      "relation": "method",
      "confidence": "EXTRACTED",
      "source_file": "app\\src\\main\\java\\com\\jarvis\\app\\JarvisAccessibilityService.kt",
      "source_location": "L51",
      "weight": 1.0
    },
    {
      "source": "jarvisaccessibilityservice_jarvisaccessibilityservice",
      "target": "jarvisaccessibilityservice_jarvisaccessibilityservice_extracttext",
      "relation": "method",
      "confidence": "EXTRACTED",
      "source_file": "app\\src\\main\\java\\com\\jarvis\\app\\JarvisAccessibilityService.kt",
      "source_location": "L56",
      "weight": 1.0
    },
    {
      "source": "app_src_main_java_com_jarvis_app_jarvisproactive_kt",
      "target": "jarvisproactive_jarvisproactive",
      "relation": "contains",
      "confidence": "EXTRACTED",
      "source_file": "app\\src\\main\\java\\com\\jarvis\\app\\JarvisProactive.kt",
      "source_location": "L11",
      "weight": 1.0
    },
    {
      "source": "jarvisproactive_jarvisproactive",
      "target": "jarvisproactive_jarvisproactive_startmonitoring",
      "relation": "method",
      "confidence": "EXTRACTED",
      "source_file": "app\\src\\main\\java\\com\\jarvis\\app\\JarvisProactive.kt",
      "source_location": "L15",
      "weight": 1.0
    },
    {
      "source": "jarvisproactive_jarvisproactive",
      "target": "jarvisproactive_jarvisproactive_stopmonitoring",
      "relation": "method",
      "confidence": "EXTRACTED",
      "source_file": "app\\src\\main\\java\\com\\jarvis\\app\\JarvisProactive.kt",
      "source_location": "L29",
      "weight": 1.0
    },
    {
      "source": "jarvisproactive_jarvisproactive",
      "target": "jarvisproactive_jarvisproactive_checkall",
      "relation": "method",
      "confidence": "EXTRACTED",
      "source_file": "app\\src\\main\\java\\com\\jarvis\\app\\JarvisProactive.kt",
      "source_location": "L34",
      "weight": 1.0
    },
    {
      "source": "jarvisproactive_jarvisproactive",
      "target": "jarvisproactive_jarvisproactive_checkcalendarreminders",
      "relation": "method",
      "confidence": "EXTRACTED",
      "source_file": "app\\src\\main\\java\\com\\jarvis\\app\\JarvisProactive.kt",
      "source_location": "L47",
      "weight": 1.0
    },
    {
      "source": "jarvisproactive_jarvisproactive",
      "target": "jarvisproactive_jarvisproactive_checkbattery",
      "relation": "method",
      "confidence": "EXTRACTED",
      "source_file": "app\\src\\main\\java\\com\\jarvis\\app\\JarvisProactive.kt",
      "source_location": "L74",
      "weight": 1.0
    },
    {
      "source": "app_src_main_java_com_jarvis_app_jarviswidgetprovider_kt",
      "target": "jarviswidgetprovider_jarviswidgetprovider",
      "relation": "contains",
      "confidence": "EXTRACTED",
      "source_file": "app\\src\\main\\java\\com\\jarvis\\app\\JarvisWidgetProvider.kt",
      "source_location": "L16",
      "weight": 1.0
    },
    {
      "source": "jarviswidgetprovider_jarviswidgetprovider",
      "target": "jarviswidgetprovider_jarviswidgetprovider_onupdate",
      "relation": "method",
      "confidence": "EXTRACTED",
      "source_file": "app\\src\\main\\java\\com\\jarvis\\app\\JarvisWidgetProvider.kt",
      "source_location": "L18",
      "weight": 1.0
    },
    {
      "source": "app_src_main_java_com_jarvis_app_jarviswidgetprovider_kt",
      "target": "jarviswidgetprovider_updatewidget",
      "relation": "contains",
      "confidence": "EXTRACTED",
      "source_file": "app\\src\\main\\java\\com\\jarvis\\app\\JarvisWidgetProvider.kt",
      "source_location": "L25",
      "weight": 1.0
    },
    {
      "source": "app_src_main_java_com_jarvis_app_mainactivity_kt",
      "target": "mainactivity_chatmessage",
      "relation": "contains",
      "confidence": "EXTRACTED",
      "source_file": "app\\src\\main\\java\\com\\jarvis\\app\\MainActivity.kt",
      "source_location": "L71",
      "weight": 1.0
    },
    {
      "source": "app_src_main_java_com_jarvis_app_mainactivity_kt",
      "target": "mainactivity_mainactivity",
      "relation": "contains",
      "confidence": "EXTRACTED",
      "source_file": "app\\src\\main\\java\\com\\jarvis\\app\\MainActivity.kt",
      "source_location": "L77",
      "weight": 1.0
    },
    {
      "source": "mainactivity_mainactivity",
      "target": "mainactivity_mainactivity_oncreate",
      "relation": "method",
      "confidence": "EXTRACTED",
      "source_file": "app\\src\\main\\java\\com\\jarvis\\app\\MainActivity.kt",
      "source_location": "L99",
      "weight": 1.0
    },
    {
      "source": "mainactivity_mainactivity",
      "target": "mainactivity_mainactivity_oninit",
      "relation": "method",
      "confidence": "EXTRACTED",
      "source_file": "app\\src\\main\\java\\com\\jarvis\\app\\MainActivity.kt",
      "source_location": "L118",
      "weight": 1.0
    },
    {
      "source": "mainactivity_mainactivity",
      "target": "mainactivity_mainactivity_ondestroy",
      "relation": "method",
      "confidence": "EXTRACTED",
      "source_file": "app\\src\\main\\java\\com\\jarvis\\app\\MainActivity.kt",
      "source_location": "L137",
      "weight": 1.0
    },
    {
      "source": "mainactivity_mainactivity",
      "target": "mainactivity_mainactivity_shutdownapp",
      "relation": "method",
      "confidence": "EXTRACTED",
      "source_file": "app\\src\\main\\java\\com\\jarvis\\app\\MainActivity.kt",
      "source_location": "L145",
      "weight": 1.0
    },
    {
      "source": "mainactivity_mainactivity",
      "target": "mainactivity_mainactivity_speakwithtts",
      "relation": "method",
      "confidence": "EXTRACTED",
      "source_file": "app\\src\\main\\java\\com\\jarvis\\app\\MainActivity.kt",
      "source_location": "L159",
      "weight": 1.0
    },
    {
      "source": "mainactivity_mainactivity",
      "target": "mainactivity_mainactivity_speakwithelevenlabs",
      "relation": "method",
      "confidence": "EXTRACTED",
      "source_file": "app\\src\\main\\java\\com\\jarvis\\app\\MainActivity.kt",
      "source_location": "L169",
      "weight": 1.0
    },
    {
      "source": "mainactivity_mainactivity",
      "target": "mainactivity_mainactivity_speaktext",
      "relation": "method",
      "confidence": "EXTRACTED",
      "source_file": "app\\src\\main\\java\\com\\jarvis\\app\\MainActivity.kt",
      "source_location": "L207",
      "weight": 1.0
    },
    {
      "source": "mainactivity_mainactivity",
      "target": "mainactivity_mainactivity_startlisteninginternal",
      "relation": "method",
      "confidence": "EXTRACTED",
      "source_file": "app\\src\\main\\java\\com\\jarvis\\app\\MainActivity.kt",
      "source_location": "L213",
      "weight": 1.0
    },
    {
      "source": "mainactivity_mainactivity",
      "target": "mainactivity_mainactivity_stoplistening",
      "relation": "method",
      "confidence": "EXTRACTED",
      "source_file": "app\\src\\main\\java\\com\\jarvis\\app\\MainActivity.kt",
      "source_location": "L276",
      "weight": 1.0
    },
    {
      "source": "mainactivity_mainactivity",
      "target": "mainactivity_mainactivity_openapp",
      "relation": "method",
      "confidence": "EXTRACTED",
      "source_file": "app\\src\\main\\java\\com\\jarvis\\app\\MainActivity.kt",
      "source_location": "L281",
      "weight": 1.0
    },
    {
      "source": "mainactivity_mainactivity",
      "target": "mainactivity_mainactivity_extractafter",
      "relation": "method",
      "confidence": "EXTRACTED",
      "source_file": "app\\src\\main\\java\\com\\jarvis\\app\\MainActivity.kt",
      "source_location": "L305",
      "weight": 1.0
    },
    {
      "source": "mainactivity_mainactivity",
      "target": "mainactivity_mainactivity_extractnumber",
      "relation": "method",
      "confidence": "EXTRACTED",
      "source_file": "app\\src\\main\\java\\com\\jarvis\\app\\MainActivity.kt",
      "source_location": "L313",
      "weight": 1.0
    },
    {
      "source": "mainactivity_mainactivity",
      "target": "mainactivity_mainactivity_extracttime",
      "relation": "method",
      "confidence": "EXTRACTED",
      "source_file": "app\\src\\main\\java\\com\\jarvis\\app\\MainActivity.kt",
      "source_location": "L324",
      "weight": 1.0
    },
    {
      "source": "mainactivity_mainactivity",
      "target": "mainactivity_mainactivity_parsehourword",
      "relation": "method",
      "confidence": "EXTRACTED",
      "source_file": "app\\src\\main\\java\\com\\jarvis\\app\\MainActivity.kt",
      "source_location": "L371",
      "weight": 1.0
    },
    {
      "source": "mainactivity_mainactivity",
      "target": "mainactivity_mainactivity_extractdate",
      "relation": "method",
      "confidence": "EXTRACTED",
      "source_file": "app\\src\\main\\java\\com\\jarvis\\app\\MainActivity.kt",
      "source_location": "L378",
      "weight": 1.0
    },
    {
      "source": "mainactivity_mainactivity",
      "target": "mainactivity_mainactivity_extracteventtitle",
      "relation": "method",
      "confidence": "EXTRACTED",
      "source_file": "app\\src\\main\\java\\com\\jarvis\\app\\MainActivity.kt",
      "source_location": "L416",
      "weight": 1.0
    },
    {
      "source": "mainactivity_mainactivity",
      "target": "mainactivity_mainactivity_readcalendarevents",
      "relation": "method",
      "confidence": "EXTRACTED",
      "source_file": "app\\src\\main\\java\\com\\jarvis\\app\\MainActivity.kt",
      "source_location": "L429",
      "weight": 1.0
    },
    {
      "source": "mainactivity_mainactivity",
      "target": "mainactivity_mainactivity_createcalendareventdirect",
      "relation": "method",
      "confidence": "EXTRACTED",
      "source_file": "app\\src\\main\\java\\com\\jarvis\\app\\MainActivity.kt",
      "source_location": "L473",
      "weight": 1.0
    },
    {
      "source": "mainactivity_mainactivity",
      "target": "mainactivity_mainactivity_deletecalendarevent",
      "relation": "method",
      "confidence": "EXTRACTED",
      "source_file": "app\\src\\main\\java\\com\\jarvis\\app\\MainActivity.kt",
      "source_location": "L494",
      "weight": 1.0
    },
    {
      "source": "mainactivity_mainactivity",
      "target": "mainactivity_mainactivity_trysetalarm",
      "relation": "method",
      "confidence": "EXTRACTED",
      "source_file": "app\\src\\main\\java\\com\\jarvis\\app\\MainActivity.kt",
      "source_location": "L521",
      "weight": 1.0
    },
    {
      "source": "mainactivity_mainactivity",
      "target": "mainactivity_mainactivity_sendmediakey",
      "relation": "method",
      "confidence": "EXTRACTED",
      "source_file": "app\\src\\main\\java\\com\\jarvis\\app\\MainActivity.kt",
      "source_location": "L553",
      "weight": 1.0
    },
    {
      "source": "mainactivity_mainactivity",
      "target": "mainactivity_mainactivity_researchtopic",
      "relation": "method",
      "confidence": "EXTRACTED",
      "source_file": "app\\src\\main\\java\\com\\jarvis\\app\\MainActivity.kt",
      "source_location": "L575",
      "weight": 1.0
    },
    {
      "source": "mainactivity_mainactivity",
      "target": "mainactivity_mainactivity_savepdf",
      "relation": "method",
      "confidence": "EXTRACTED",
      "source_file": "app\\src\\main\\java\\com\\jarvis\\app\\MainActivity.kt",
      "source_location": "L689",
      "weight": 1.0
    },
    {
      "source": "mainactivity_mainactivity",
      "target": "mainactivity_mainactivity_getweather",
      "relation": "method",
      "confidence": "EXTRACTED",
      "source_file": "app\\src\\main\\java\\com\\jarvis\\app\\MainActivity.kt",
      "source_location": "L783",
      "weight": 1.0
    },
    {
      "source": "mainactivity_mainactivity",
      "target": "mainactivity_mainactivity_getforecast",
      "relation": "method",
      "confidence": "EXTRACTED",
      "source_file": "app\\src\\main\\java\\com\\jarvis\\app\\MainActivity.kt",
      "source_location": "L808",
      "weight": 1.0
    },
    {
      "source": "mainactivity_mainactivity",
      "target": "mainactivity_mainactivity_gettopheadlines",
      "relation": "method",
      "confidence": "EXTRACTED",
      "source_file": "app\\src\\main\\java\\com\\jarvis\\app\\MainActivity.kt",
      "source_location": "L844",
      "weight": 1.0
    },
    {
      "source": "mainactivity_mainactivity",
      "target": "mainactivity_mainactivity_handlevoicecommand",
      "relation": "method",
      "confidence": "EXTRACTED",
      "source_file": "app\\src\\main\\java\\com\\jarvis\\app\\MainActivity.kt",
      "source_location": "L888",
      "weight": 1.0
    },
    {
      "source": "mainactivity_mainactivity",
      "target": "mainactivity_mainactivity_jarvisscreen",
      "relation": "method",
      "confidence": "EXTRACTED",
      "source_file": "app\\src\\main\\java\\com\\jarvis\\app\\MainActivity.kt",
      "source_location": "L1832",
      "weight": 1.0
    },
    {
      "source": "mainactivity_mainactivity",
      "target": "mainactivity_mainactivity_phasecolor",
      "relation": "method",
      "confidence": "EXTRACTED",
      "source_file": "app\\src\\main\\java\\com\\jarvis\\app\\MainActivity.kt",
      "source_location": "L2085",
      "weight": 1.0
    },
    {
      "source": "mainactivity_mainactivity",
      "target": "mainactivity_mainactivity_arcreactormk6",
      "relation": "method",
      "confidence": "EXTRACTED",
      "source_file": "app\\src\\main\\java\\com\\jarvis\\app\\MainActivity.kt",
      "source_location": "L2093",
      "weight": 1.0
    },
    {
      "source": "mainactivity_mainactivity",
      "target": "mainactivity_mainactivity_waveformbar",
      "relation": "method",
      "confidence": "EXTRACTED",
      "source_file": "app\\src\\main\\java\\com\\jarvis\\app\\MainActivity.kt",
      "source_location": "L2289",
      "weight": 1.0
    },
    {
      "source": "mainactivity_mainactivity",
      "target": "mainactivity_mainactivity_topbar",
      "relation": "method",
      "confidence": "EXTRACTED",
      "source_file": "app\\src\\main\\java\\com\\jarvis\\app\\MainActivity.kt",
      "source_location": "L2312",
      "weight": 1.0
    },
    {
      "source": "mainactivity_mainactivity",
      "target": "mainactivity_mainactivity_statusgridwide",
      "relation": "method",
      "confidence": "EXTRACTED",
      "source_file": "app\\src\\main\\java\\com\\jarvis\\app\\MainActivity.kt",
      "source_location": "L2337",
      "weight": 1.0
    },
    {
      "source": "mainactivity_mainactivity",
      "target": "mainactivity_mainactivity_statcard",
      "relation": "method",
      "confidence": "EXTRACTED",
      "source_file": "app\\src\\main\\java\\com\\jarvis\\app\\MainActivity.kt",
      "source_location": "L2356",
      "weight": 1.0
    },
    {
      "source": "mainactivity_mainactivity",
      "target": "mainactivity_mainactivity_metricpanel",
      "relation": "method",
      "confidence": "EXTRACTED",
      "source_file": "app\\src\\main\\java\\com\\jarvis\\app\\MainActivity.kt",
      "source_location": "L2370",
      "weight": 1.0
    },
    {
      "source": "mainactivity_mainactivity",
      "target": "mainactivity_mainactivity_metricrow",
      "relation": "method",
      "confidence": "EXTRACTED",
      "source_file": "app\\src\\main\\java\\com\\jarvis\\app\\MainActivity.kt",
      "source_location": "L2393",
      "weight": 1.0
    },
    {
      "source": "mainactivity_mainactivity",
      "target": "mainactivity_mainactivity_chatheader",
      "relation": "method",
      "confidence": "EXTRACTED",
      "source_file": "app\\src\\main\\java\\com\\jarvis\\app\\MainActivity.kt",
      "source_location": "L2411",
      "weight": 1.0
    },
    {
      "source": "mainactivity_mainactivity",
      "target": "mainactivity_mainactivity_phasechip",
      "relation": "method",
      "confidence": "EXTRACTED",
      "source_file": "app\\src\\main\\java\\com\\jarvis\\app\\MainActivity.kt",
      "source_location": "L2430",
      "weight": 1.0
    },
    {
      "source": "mainactivity_mainactivity",
      "target": "mainactivity_mainactivity_messagebubble",
      "relation": "method",
      "confidence": "EXTRACTED",
      "source_file": "app\\src\\main\\java\\com\\jarvis\\app\\MainActivity.kt",
      "source_location": "L2443",
      "weight": 1.0
    },
    {
      "source": "mainactivity_mainactivity",
      "target": "mainactivity_mainactivity_inputbar",
      "relation": "method",
      "confidence": "EXTRACTED",
      "source_file": "app\\src\\main\\java\\com\\jarvis\\app\\MainActivity.kt",
      "source_location": "L2473",
      "weight": 1.0
    },
    {
      "source": "mainactivity_mainactivity",
      "target": "mainactivity_mainactivity_jarvistheme",
      "relation": "method",
      "confidence": "EXTRACTED",
      "source_file": "app\\src\\main\\java\\com\\jarvis\\app\\MainActivity.kt",
      "source_location": "L2514",
      "weight": 1.0
    },
    {
      "source": "mainactivity_mainactivity",
      "target": "mainactivity_mainactivity_loadmemoryfromfirebase",
      "relation": "method",
      "confidence": "EXTRACTED",
      "source_file": "app\\src\\main\\java\\com\\jarvis\\app\\MainActivity.kt",
      "source_location": "L2526",
      "weight": 1.0
    },
    {
      "source": "mainactivity_mainactivity",
      "target": "mainactivity_mainactivity_syncmessagetofirebase",
      "relation": "method",
      "confidence": "EXTRACTED",
      "source_file": "app\\src\\main\\java\\com\\jarvis\\app\\MainActivity.kt",
      "source_location": "L2536",
      "weight": 1.0
    },
    {
      "source": "mainactivity_mainactivity",
      "target": "mainactivity_mainactivity_saveconversationtofirebase",
      "relation": "method",
      "confidence": "EXTRACTED",
      "source_file": "app\\src\\main\\java\\com\\jarvis\\app\\MainActivity.kt",
      "source_location": "L2544",
      "weight": 1.0
    },
    {
      "source": "mainactivity_mainactivity",
      "target": "mainactivity_mainactivity_loadconversationfromfirebase",
      "relation": "method",
      "confidence": "EXTRACTED",
      "source_file": "app\\src\\main\\java\\com\\jarvis\\app\\MainActivity.kt",
      "source_location": "L2552",
      "weight": 1.0
    },
    {
      "source": "mainactivity_mainactivity",
      "target": "mainactivity_mainactivity_sendtojarvis",
      "relation": "method",
      "confidence": "EXTRACTED",
      "source_file": "app\\src\\main\\java\\com\\jarvis\\app\\MainActivity.kt",
      "source_location": "L2571",
      "weight": 1.0
    },
    {
      "source": "mainactivity_mainactivity",
      "target": "mainactivity_mainactivity_getgreeting",
      "relation": "method",
      "confidence": "EXTRACTED",
      "source_file": "app\\src\\main\\java\\com\\jarvis\\app\\MainActivity.kt",
      "source_location": "L2701",
      "weight": 1.0
    },
    {
      "source": "app_src_main_java_com_jarvis_app_ui_theme_theme_kt",
      "target": "theme_jarvistheme",
      "relation": "contains",
      "confidence": "EXTRACTED",
      "source_file": "app\\src\\main\\java\\com\\jarvis\\app\\ui\\theme\\Theme.kt",
      "source_location": "L36",
      "weight": 1.0
    },
    {
      "source": "app_src_test_java_com_jarvis_app_exampleunittest_kt",
      "target": "exampleunittest_exampleunittest",
      "relation": "contains",
      "confidence": "EXTRACTED",
      "source_file": "app\\src\\test\\java\\com\\jarvis\\app\\ExampleUnitTest.kt",
      "source_location": "L12",
      "weight": 1.0
    },
    {
      "source": "exampleunittest_exampleunittest",
      "target": "exampleunittest_exampleunittest_addition_iscorrect",
      "relation": "method",
      "confidence": "EXTRACTED",
      "source_file": "app\\src\\test\\java\\com\\jarvis\\app\\ExampleUnitTest.kt",
      "source_location": "L13",
      "weight": 1.0
    },
    {
      "source": "ic_launcher_hdpi",
      "target": "concept_android_robot_icon",
      "relation": "references",
      "confidence": "EXTRACTED",
      "confidence_score": 1.0,
      "source_file": "app/src/main/res/mipmap-hdpi/ic_launcher.webp",
      "source_location": null,
      "weight": 1.0
    },
    {
      "source": "ic_launcher_mdpi",
      "target": "concept_android_robot_icon",
      "relation": "references",
      "confidence": "EXTRACTED",
      "confidence_score": 1.0,
      "source_file": "app/src/main/res/mipmap-mdpi/ic_launcher.webp",
      "source_location": null,
      "weight": 1.0
    },
    {
      "source": "ic_launcher_xhdpi",
      "target": "concept_android_robot_icon",
      "relation": "references",
      "confidence": "EXTRACTED",
      "confidence_score": 1.0,
      "source_file": "app/src/main/res/mipmap-xhdpi/ic_launcher.webp",
      "source_location": null,
      "weight": 1.0
    },
    {
      "source": "ic_launcher_xxhdpi",
      "target": "concept_android_robot_icon",
      "relation": "references",
      "confidence": "EXTRACTED",
      "confidence_score": 1.0,
      "source_file": "app/src/main/res/mipmap-xxhdpi/ic_launcher.webp",
      "source_location": null,
      "weight": 1.0
    },
    {
      "source": "ic_launcher_xxxhdpi",
      "target": "concept_android_robot_icon",
      "relation": "references",
      "confidence": "EXTRACTED",
      "confidence_score": 1.0,
      "source_file": "app/src/main/res/mipmap-xxxhdpi/ic_launcher.webp",
      "source_location": null,
      "weight": 1.0
    },
    {
      "source": "ic_launcher_hdpi",
      "target": "concept_green_grid_background",
      "relation": "references",
      "confidence": "EXTRACTED",
      "confidence_score": 1.0,
      "source_file": "app/src/main/res/mipmap-hdpi/ic_launcher.webp",
      "source_location": null,
      "weight": 1.0
    },
    {
      "source": "ic_launcher_mdpi",
      "target": "concept_green_grid_background",
      "relation": "references",
      "confidence": "EXTRACTED",
      "confidence_score": 1.0,
      "source_file": "app/src/main/res/mipmap-mdpi/ic_launcher.webp",
      "source_location": null,
      "weight": 1.0
    },
    {
      "source": "ic_launcher_xhdpi",
      "target": "concept_green_grid_background",
      "relation": "references",
      "confidence": "EXTRACTED",
      "confidence_score": 1.0,
      "source_file": "app/src/main/res/mipmap-xhdpi/ic_launcher.webp",
      "source_location": null,
      "weight": 1.0
    },
    {
      "source": "ic_launcher_xxhdpi",
      "target": "concept_green_grid_background",
      "relation": "references",
      "confidence": "EXTRACTED",
      "confidence_score": 1.0,
      "source_file": "app/src/main/res/mipmap-xxhdpi/ic_launcher.webp",
      "source_location": null,
      "weight": 1.0
    },
    {
      "source": "ic_launcher_xxxhdpi",
      "target": "concept_green_grid_background",
      "relation": "references",
      "confidence": "EXTRACTED",
      "confidence_score": 1.0,
      "source_file": "app/src/main/res/mipmap-xxxhdpi/ic_launcher.webp",
      "source_location": null,
      "weight": 1.0
    },
    {
      "source": "ic_launcher_hdpi",
      "target": "concept_default_android_branding",
      "relation": "conceptually_related_to",
      "confidence": "INFERRED",
      "confidence_score": 0.9,
      "source_file": "app/src/main/res/mipmap-hdpi/ic_launcher.webp",
      "source_location": null,
      "weight": 0.9
    },
    {
      "source": "ic_launcher_mdpi",
      "target": "concept_default_android_branding",
      "relation": "conceptually_related_to",
      "confidence": "INFERRED",
      "confidence_score": 0.9,
      "source_file": "app/src/main/res/mipmap-mdpi/ic_launcher.webp",
      "source_location": null,
      "weight": 0.9
    },
    {
      "source": "ic_launcher_xhdpi",
      "target": "concept_default_android_branding",
      "relation": "conceptually_related_to",
      "confidence": "INFERRED",
      "confidence_score": 0.9,
      "source_file": "app/src/main/res/mipmap-xhdpi/ic_launcher.webp",
      "source_location": null,
      "weight": 0.9
    },
    {
      "source": "ic_launcher_xxhdpi",
      "target": "concept_default_android_branding",
      "relation": "conceptually_related_to",
      "confidence": "INFERRED",
      "confidence_score": 0.9,
      "source_file": "app/src/main/res/mipmap-xxhdpi/ic_launcher.webp",
      "source_location": null,
      "weight": 0.9
    },
    {
      "source": "ic_launcher_xxxhdpi",
      "target": "concept_default_android_branding",
      "relation": "conceptually_related_to",
      "confidence": "INFERRED",
      "confidence_score": 0.9,
      "source_file": "app/src/main/res/mipmap-xxxhdpi/ic_launcher.webp",
      "source_location": null,
      "weight": 0.9
    },
    {
      "source": "ic_launcher_hdpi",
      "target": "concept_mipmap_density_set",
      "relation": "conceptually_related_to",
      "confidence": "EXTRACTED",
      "confidence_score": 1.0,
      "source_file": "app/src/main/res/mipmap-hdpi/ic_launcher.webp",
      "source_location": null,
      "weight": 1.0
    },
    {
      "source": "ic_launcher_mdpi",
      "target": "concept_mipmap_density_set",
      "relation": "conceptually_related_to",
      "confidence": "EXTRACTED",
      "confidence_score": 1.0,
      "source_file": "app/src/main/res/mipmap-mdpi/ic_launcher.webp",
      "source_location": null,
      "weight": 1.0
    },
    {
      "source": "ic_launcher_xhdpi",
      "target": "concept_mipmap_density_set",
      "relation": "conceptually_related_to",
      "confidence": "EXTRACTED",
      "confidence_score": 1.0,
      "source_file": "app/src/main/res/mipmap-xhdpi/ic_launcher.webp",
      "source_location": null,
      "weight": 1.0
    },
    {
      "source": "ic_launcher_xxhdpi",
      "target": "concept_mipmap_density_set",
      "relation": "conceptually_related_to",
      "confidence": "EXTRACTED",
      "confidence_score": 1.0,
      "source_file": "app/src/main/res/mipmap-xxhdpi/ic_launcher.webp",
      "source_location": null,
      "weight": 1.0
    },
    {
      "source": "ic_launcher_xxxhdpi",
      "target": "concept_mipmap_density_set",
      "relation": "conceptually_related_to",
      "confidence": "EXTRACTED",
      "confidence_score": 1.0,
      "source_file": "app/src/main/res/mipmap-xxxhdpi/ic_launcher.webp",
      "source_location": null,
      "weight": 1.0
    },
    {
      "source": "ic_launcher_hdpi",
      "target": "ic_launcher_mdpi",
      "relation": "semantically_similar_to",
      "confidence": "EXTRACTED",
      "confidence_score": 1.0,
      "source_file": "app/src/main/res/mipmap-hdpi/ic_launcher.webp",
      "source_location": null,
      "weight": 1.0
    },
    {
      "source": "ic_launcher_hdpi",
      "target": "ic_launcher_xhdpi",
      "relation": "semantically_similar_to",
      "confidence": "EXTRACTED",
      "confidence_score": 1.0,
      "source_file": "app/src/main/res/mipmap-hdpi/ic_launcher.webp",
      "source_location": null,
      "weight": 1.0
    },
    {
      "source": "ic_launcher_hdpi",
      "target": "ic_launcher_xxhdpi",
      "relation": "semantically_similar_to",
      "confidence": "EXTRACTED",
      "confidence_score": 1.0,
      "source_file": "app/src/main/res/mipmap-hdpi/ic_launcher.webp",
      "source_location": null,
      "weight": 1.0
    },
    {
      "source": "ic_launcher_hdpi",
      "target": "ic_launcher_xxxhdpi",
      "relation": "semantically_similar_to",
      "confidence": "EXTRACTED",
      "confidence_score": 1.0,
      "source_file": "app/src/main/res/mipmap-hdpi/ic_launcher.webp",
      "source_location": null,
      "weight": 1.0
    },
    {
      "source": "ic_launcher_mdpi",
      "target": "ic_launcher_xhdpi",
      "relation": "semantically_similar_to",
      "confidence": "EXTRACTED",
      "confidence_score": 1.0,
      "source_file": "app/src/main/res/mipmap-mdpi/ic_launcher.webp",
      "source_location": null,
      "weight": 1.0
    },
    {
      "source": "ic_launcher_mdpi",
      "target": "ic_launcher_xxhdpi",
      "relation": "semantically_similar_to",
      "confidence": "EXTRACTED",
      "confidence_score": 1.0,
      "source_file": "app/src/main/res/mipmap-mdpi/ic_launcher.webp",
      "source_location": null,
      "weight": 1.0
    },
    {
      "source": "ic_launcher_mdpi",
      "target": "ic_launcher_xxxhdpi",
      "relation": "semantically_similar_to",
      "confidence": "EXTRACTED",
      "confidence_score": 1.0,
      "source_file": "app/src/main/res/mipmap-mdpi/ic_launcher.webp",
      "source_location": null,
      "weight": 1.0
    },
    {
      "source": "ic_launcher_xhdpi",
      "target": "ic_launcher_xxhdpi",
      "relation": "semantically_similar_to",
      "confidence": "EXTRACTED",
      "confidence_score": 1.0,
      "source_file": "app/src/main/res/mipmap-xhdpi/ic_launcher.webp",
      "source_location": null,
      "weight": 1.0
    },
    {
      "source": "ic_launcher_xhdpi",
      "target": "ic_launcher_xxxhdpi",
      "relation": "semantically_similar_to",
      "confidence": "EXTRACTED",
      "confidence_score": 1.0,
      "source_file": "app/src/main/res/mipmap-xhdpi/ic_launcher.webp",
      "source_location": null,
      "weight": 1.0
    },
    {
      "source": "ic_launcher_xxhdpi",
      "target": "ic_launcher_xxxhdpi",
      "relation": "semantically_similar_to",
      "confidence": "EXTRACTED",
      "confidence_score": 1.0,
      "source_file": "app/src/main/res/mipmap-xxhdpi/ic_launcher.webp",
      "source_location": null,
      "weight": 1.0
    },
    {
      "source": "concept_default_android_branding",
      "target": "concept_android_robot_icon",
      "relation": "conceptually_related_to",
      "confidence": "INFERRED",
      "confidence_score": 0.85,
      "source_file": null,
      "source_location": null,
      "weight": 0.85
    },
    {
      "source": "ic_launcher_round_hdpi",
      "target": "ic_launcher_round_mdpi",
      "relation": "semantically_similar_to",
      "confidence": "EXTRACTED",
      "confidence_score": 1.0,
      "source_file": "app/src/main/res/mipmap-hdpi/ic_launcher_round.webp",
      "source_location": null,
      "weight": 1.0
    },
    {
      "source": "ic_launcher_round_hdpi",
      "target": "ic_launcher_round_xhdpi",
      "relation": "semantically_similar_to",
      "confidence": "EXTRACTED",
      "confidence_score": 1.0,
      "source_file": "app/src/main/res/mipmap-hdpi/ic_launcher_round.webp",
      "source_location": null,
      "weight": 1.0
    },
    {
      "source": "ic_launcher_round_hdpi",
      "target": "ic_launcher_round_xxhdpi",
      "relation": "semantically_similar_to",
      "confidence": "EXTRACTED",
      "confidence_score": 1.0,
      "source_file": "app/src/main/res/mipmap-hdpi/ic_launcher_round.webp",
      "source_location": null,
      "weight": 1.0
    },
    {
      "source": "ic_launcher_round_hdpi",
      "target": "ic_launcher_round_xxxhdpi",
      "relation": "semantically_similar_to",
      "confidence": "EXTRACTED",
      "confidence_score": 1.0,
      "source_file": "app/src/main/res/mipmap-hdpi/ic_launcher_round.webp",
      "source_location": null,
      "weight": 1.0
    },
    {
      "source": "ic_launcher_round_mdpi",
      "target": "ic_launcher_round_xhdpi",
      "relation": "semantically_similar_to",
      "confidence": "EXTRACTED",
      "confidence_score": 1.0,
      "source_file": "app/src/main/res/mipmap-mdpi/ic_launcher_round.webp",
      "source_location": null,
      "weight": 1.0
    },
    {
      "source": "ic_launcher_round_mdpi",
      "target": "ic_launcher_round_xxhdpi",
      "relation": "semantically_similar_to",
      "confidence": "EXTRACTED",
      "confidence_score": 1.0,
      "source_file": "app/src/main/res/mipmap-mdpi/ic_launcher_round.webp",
      "source_location": null,
      "weight": 1.0
    },
    {
      "source": "ic_launcher_round_mdpi",
      "target": "ic_launcher_round_xxxhdpi",
      "relation": "semantically_similar_to",
      "confidence": "EXTRACTED",
      "confidence_score": 1.0,
      "source_file": "app/src/main/res/mipmap-mdpi/ic_launcher_round.webp",
      "source_location": null,
      "weight": 1.0
    },
    {
      "source": "ic_launcher_round_xhdpi",
      "target": "ic_launcher_round_xxhdpi",
      "relation": "semantically_similar_to",
      "confidence": "EXTRACTED",
      "confidence_score": 1.0,
      "source_file": "app/src/main/res/mipmap-xhdpi/ic_launcher_round.webp",
      "source_location": null,
      "weight": 1.0
    },
    {
      "source": "ic_launcher_round_xhdpi",
      "target": "ic_launcher_round_xxxhdpi",
      "relation": "semantically_similar_to",
      "confidence": "EXTRACTED",
      "confidence_score": 1.0,
      "source_file": "app/src/main/res/mipmap-xhdpi/ic_launcher_round.webp",
      "source_location": null,
      "weight": 1.0
    },
    {
      "source": "ic_launcher_round_xxhdpi",
      "target": "ic_launcher_round_xxxhdpi",
      "relation": "semantically_similar_to",
      "confidence": "EXTRACTED",
      "confidence_score": 1.0,
      "source_file": "app/src/main/res/mipmap-xxhdpi/ic_launcher_round.webp",
      "source_location": null,
      "weight": 1.0
    },
    {
      "source": "ic_launcher_round_hdpi",
      "target": "concept_android_robot_icon",
      "relation": "references",
      "confidence": "EXTRACTED",
      "confidence_score": 1.0,
      "source_file": "app/src/main/res/mipmap-hdpi/ic_launcher_round.webp",
      "source_location": null,
      "weight": 1.0
    },
    {
      "source": "ic_launcher_round_mdpi",
      "target": "concept_android_robot_icon",
      "relation": "references",
      "confidence": "EXTRACTED",
      "confidence_score": 1.0,
      "source_file": "app/src/main/res/mipmap-mdpi/ic_launcher_round.webp",
      "source_location": null,
      "weight": 1.0
    },
    {
      "source": "ic_launcher_round_xhdpi",
      "target": "concept_android_robot_icon",
      "relation": "references",
      "confidence": "EXTRACTED",
      "confidence_score": 1.0,
      "source_file": "app/src/main/res/mipmap-xhdpi/ic_launcher_round.webp",
      "source_location": null,
      "weight": 1.0
    },
    {
      "source": "ic_launcher_round_xxhdpi",
      "target": "concept_android_robot_icon",
      "relation": "references",
      "confidence": "EXTRACTED",
      "confidence_score": 1.0,
      "source_file": "app/src/main/res/mipmap-xxhdpi/ic_launcher_round.webp",
      "source_location": null,
      "weight": 1.0
    },
    {
      "source": "ic_launcher_round_xxxhdpi",
      "target": "concept_android_robot_icon",
      "relation": "references",
      "confidence": "EXTRACTED",
      "confidence_score": 1.0,
      "source_file": "app/src/main/res/mipmap-xxxhdpi/ic_launcher_round.webp",
      "source_location": null,
      "weight": 1.0
    },
    {
      "source": "ic_launcher_round_hdpi",
      "target": "concept_green_palette",
      "relation": "references",
      "confidence": "EXTRACTED",
      "confidence_score": 1.0,
      "source_file": "app/src/main/res/mipmap-hdpi/ic_launcher_round.webp",
      "source_location": null,
      "weight": 1.0
    },
    {
      "source": "ic_launcher_round_mdpi",
      "target": "concept_green_palette",
      "relation": "references",
      "confidence": "EXTRACTED",
      "confidence_score": 1.0,
      "source_file": "app/src/main/res/mipmap-mdpi/ic_launcher_round.webp",
      "source_location": null,
      "weight": 1.0
    },
    {
      "source": "ic_launcher_round_xhdpi",
      "target": "concept_green_palette",
      "relation": "references",
      "confidence": "EXTRACTED",
      "confidence_score": 1.0,
      "source_file": "app/src/main/res/mipmap-xhdpi/ic_launcher_round.webp",
      "source_location": null,
      "weight": 1.0
    },
    {
      "source": "ic_launcher_round_xxhdpi",
      "target": "concept_green_palette",
      "relation": "references",
      "confidence": "EXTRACTED",
      "confidence_score": 1.0,
      "source_file": "app/src/main/res/mipmap-xxhdpi/ic_launcher_round.webp",
      "source_location": null,
      "weight": 1.0
    },
    {
      "source": "ic_launcher_round_xxxhdpi",
      "target": "concept_green_palette",
      "relation": "references",
      "confidence": "EXTRACTED",
      "confidence_score": 1.0,
      "source_file": "app/src/main/res/mipmap-xxxhdpi/ic_launcher_round.webp",
      "source_location": null,
      "weight": 1.0
    },
    {
      "source": "ic_launcher_round_hdpi",
      "target": "concept_round_icon_shape",
      "relation": "references",
      "confidence": "EXTRACTED",
      "confidence_score": 1.0,
      "source_file": "app/src/main/res/mipmap-hdpi/ic_launcher_round.webp",
      "source_location": null,
      "weight": 1.0
    },
    {
      "source": "ic_launcher_round_mdpi",
      "target": "concept_round_icon_shape",
      "relation": "references",
      "confidence": "EXTRACTED",
      "confidence_score": 1.0,
      "source_file": "app/src/main/res/mipmap-mdpi/ic_launcher_round.webp",
      "source_location": null,
      "weight": 1.0
    },
    {
      "source": "ic_launcher_round_xhdpi",
      "target": "concept_round_icon_shape",
      "relation": "references",
      "confidence": "EXTRACTED",
      "confidence_score": 1.0,
      "source_file": "app/src/main/res/mipmap-xhdpi/ic_launcher_round.webp",
      "source_location": null,
      "weight": 1.0
    },
    {
      "source": "ic_launcher_round_xxhdpi",
      "target": "concept_round_icon_shape",
      "relation": "references",
      "confidence": "EXTRACTED",
      "confidence_score": 1.0,
      "source_file": "app/src/main/res/mipmap-xxhdpi/ic_launcher_round.webp",
      "source_location": null,
      "weight": 1.0
    },
    {
      "source": "ic_launcher_round_xxxhdpi",
      "target": "concept_round_icon_shape",
      "relation": "references",
      "confidence": "EXTRACTED",
      "confidence_score": 1.0,
      "source_file": "app/src/main/res/mipmap-xxxhdpi/ic_launcher_round.webp",
      "source_location": null,
      "weight": 1.0
    },
    {
      "source": "ic_launcher_round_hdpi",
      "target": "concept_default_android_branding",
      "relation": "conceptually_related_to",
      "confidence": "INFERRED",
      "confidence_score": 0.95,
      "source_file": "app/src/main/res/mipmap-hdpi/ic_launcher_round.webp",
      "source_location": null,
      "weight": 0.95
    },
    {
      "source": "ic_launcher_round_mdpi",
      "target": "concept_default_android_branding",
      "relation": "conceptually_related_to",
      "confidence": "INFERRED",
      "confidence_score": 0.95,
      "source_file": "app/src/main/res/mipmap-mdpi/ic_launcher_round.webp",
      "source_location": null,
      "weight": 0.95
    },
    {
      "source": "ic_launcher_round_xhdpi",
      "target": "concept_default_android_branding",
      "relation": "conceptually_related_to",
      "confidence": "INFERRED",
      "confidence_score": 0.95,
      "source_file": "app/src/main/res/mipmap-xhdpi/ic_launcher_round.webp",
      "source_location": null,
      "weight": 0.95
    },
    {
      "source": "ic_launcher_round_xxhdpi",
      "target": "concept_default_android_branding",
      "relation": "conceptually_related_to",
      "confidence": "INFERRED",
      "confidence_score": 0.95,
      "source_file": "app/src/main/res/mipmap-xxhdpi/ic_launcher_round.webp",
      "source_location": null,
      "weight": 0.95
    },
    {
      "source": "ic_launcher_round_xxxhdpi",
      "target": "concept_default_android_branding",
      "relation": "conceptually_related_to",
      "confidence": "INFERRED",
      "confidence_score": 0.95,
      "source_file": "app/src/main/res/mipmap-xxxhdpi/ic_launcher_round.webp",
      "source_location": null,
      "weight": 0.95
    },
    {
      "source": "ic_launcher_round_hdpi",
      "target": "concept_grid_background",
      "relation": "references",
      "confidence": "EXTRACTED",
      "confidence_score": 1.0,
      "source_file": "app/src/main/res/mipmap-hdpi/ic_launcher_round.webp",
      "source_location": null,
      "weight": 1.0
    },
    {
      "source": "ic_launcher_round_mdpi",
      "target": "concept_grid_background",
      "relation": "references",
      "confidence": "EXTRACTED",
      "confidence_score": 1.0,
      "source_file": "app/src/main/res/mipmap-mdpi/ic_launcher_round.webp",
      "source_location": null,
      "weight": 1.0
    },
    {
      "source": "ic_launcher_round_xhdpi",
      "target": "concept_grid_background",
      "relation": "references",
      "confidence": "EXTRACTED",
      "confidence_score": 1.0,
      "source_file": "app/src/main/res/mipmap-xhdpi/ic_launcher_round.webp",
      "source_location": null,
      "weight": 1.0
    },
    {
      "source": "ic_launcher_round_xxhdpi",
      "target": "concept_grid_background",
      "relation": "references",
      "confidence": "EXTRACTED",
      "confidence_score": 1.0,
      "source_file": "app/src/main/res/mipmap-xxhdpi/ic_launcher_round.webp",
      "source_location": null,
      "weight": 1.0
    },
    {
      "source": "ic_launcher_round_xxxhdpi",
      "target": "concept_grid_background",
      "relation": "references",
      "confidence": "EXTRACTED",
      "confidence_score": 1.0,
      "source_file": "app/src/main/res/mipmap-xxxhdpi/ic_launcher_round.webp",
      "source_location": null,
      "weight": 1.0
    },
    {
      "source": "concept_default_android_branding",
      "target": "concept_android_robot_icon",
      "relation": "conceptually_related_to",
      "confidence": "INFERRED",
      "confidence_score": 0.9,
      "source_file": "app/src/main/res/mipmap-xxxhdpi/ic_launcher_round.webp",
      "source_location": null,
      "weight": 0.9
    },
    {
      "source": "concept_android_robot_icon",
      "target": "concept_green_palette",
      "relation": "conceptually_related_to",
      "confidence": "INFERRED",
      "confidence_score": 0.85,
      "source_file": "app/src/main/res/mipmap-xxxhdpi/ic_launcher_round.webp",
      "source_location": null,
      "weight": 0.85
    },
    {
      "source": "concept_round_icon_shape",
      "target": "concept_default_android_branding",
      "relation": "conceptually_related_to",
      "confidence": "INFERRED",
      "confidence_score": 0.8,
      "source_file": "app/src/main/res/mipmap-xxxhdpi/ic_launcher_round.webp",
      "source_location": null,
      "weight": 0.8
    }
  ],
  "hyperedges": [],
  "input_tokens": 0,
  "output_tokens": 0
}